{"name":"axios-http-adapter","version":"0.0.3","description":"This is an adapter for unifiying an interface for http.","main":"./dist/AxiosHttpAdapter.js","typings":"./dist/AxiosHttpAdapter.d.ts","dependencies":{"axios":"^0.12.0","typescript-dotnet-umd":"^3.2.0","typescript":"^1.8.10"},"optionalDependencies":{"typescript":"^1.8.10"},"scripts":{"test":"echo \"Error: no test specified\" && exit 1"},"repository":"https://github.com/electricessence/axios-http-adapter","keywords":["http","axios","adapter","TypeScript.NET"],"license":"MIT","homepage":"https://github.com/electricessence/axios-http-adapter#readme","gitHead":"93de70f951ac17f933996f1b769b6596075c7cc4","versions":[{"number":"0.0.1","date":"2016-06-26T21:15:27.930Z"},{"number":"0.0.2","date":"2016-06-26T21:56:53.146Z"},{"number":"0.0.3","date":"2016-06-26T22:09:50.958Z"}],"readme":"ERROR: No README data found!","created":"2016-06-26T21:15:27.930Z","modified":"2016-06-26T22:09:50.958Z","lastPublisher":{"name":"electricessence","email":"npm@electrified.net"},"owners":[{"name":"electricessence","email":"npm@electrified.net"}],"other":{"_attachments":{},"_from":".","_id":"axios-http-adapter","_nodeVersion":"5.6.0","_npmOperationalInternal":{"host":"packages-16-east.internal.npmjs.com","tmp":"tmp/axios-http-adapter-0.0.3.tgz_1466978987035_0.22497487417422235"},"_npmUser":{"name":"electricessence","email":"npm@electrified.net"},"_npmVersion":"3.6.0","_rev":"1-20c96c3afe96f63ff165e570a0a8de5a","_shasum":"b33b7d152648dcc84b84a022b1ac85beff0f8dda","author":{"name":"electricessence"},"bugs":{"url":"https://github.com/electricessence/axios-http-adapter/issues"},"directories":{},"dist-tags":{"latest":"0.0.3"},"dist":{"shasum":"b33b7d152648dcc84b84a022b1ac85beff0f8dda","tarball":"http://registry.npmjs.org/axios-http-adapter/-/axios-http-adapter-0.0.3.tgz"},"maintainers":[{"name":"electricessence","email":"npm@electrified.net"}],"readmeFilename":"","time":{"modified":"2016-06-26T22:09:50.958Z","created":"2016-06-26T21:15:27.930Z","0.0.1":"2016-06-26T21:15:27.930Z","0.0.2":"2016-06-26T21:56:53.146Z","0.0.3":"2016-06-26T22:09:50.958Z"}}}