{"name":"ceramic-dictionary-parser","version":"0.2.0","description":"Parse an Http Request Body and convert them into entities using Ceramic","repository":"https://github.com/jeswin/ceramic-dictionary-parser","main":"lib/ceramic-dictionary-parser","dependencies":{"sanitizer":"*"},"devDependencies":{"istanbul-harmony":"0","mocha":"^2.0.0"},"engines":{"node":">= 0.11.9"},"keywords":["serialization"],"license":"GPL-3.0+","gitHead":"6cab7c723943efcadbf4ecec38b69faf78c48444","homepage":"https://github.com/jeswin/ceramic-dictionary-parser","scripts":{},"versions":[{"number":"0.1.1","date":"2015-01-16T06:13:21.089Z"},{"number":"0.2.0","date":"2015-04-15T08:26:41.587Z"}],"readme":"# ceramic-http-parser\nParse an Http Request Body and convert them into entities using Ceramic\n","created":"2015-01-16T06:13:21.089Z","modified":"2015-04-15T08:26:41.587Z","lastPublisher":{"name":"jeswin","email":"jeswinpk@agilehead.com"},"owners":[{"name":"jeswin","email":"jeswinpk@agilehead.com"}],"other":{"_attachments":{},"_from":".","_id":"ceramic-dictionary-parser","_nodeVersion":"1.4.3","_npmUser":{"name":"jeswin","email":"jeswinpk@agilehead.com"},"_npmVersion":"2.6.1","_rev":"1-224ae977f113d3fde2a336885f0eaf36","_shasum":"72f373a85d733f220a82c43d36c066e53a09f91e","author":{"name":"Jeswin Kumar","email":"jeswinpk@agilehead.com"},"bugs":{"url":"https://github.com/jeswin/ceramic-dictionary-parser/issues"},"directories":{},"dist-tags":{"latest":"0.2.0"},"dist":{"shasum":"72f373a85d733f220a82c43d36c066e53a09f91e","tarball":"http://registry.npmjs.org/ceramic-dictionary-parser/-/ceramic-dictionary-parser-0.2.0.tgz"},"maintainers":[{"name":"jeswin","email":"jeswinpk@agilehead.com"}],"readmeFilename":"README.md","time":{"modified":"2015-04-15T08:26:41.587Z","created":"2015-01-16T06:13:21.089Z","0.1.1":"2015-01-16T06:13:21.089Z","0.2.0":"2015-04-15T08:26:41.587Z"}}}