{"name":"express-accepts","version":"0.1.0","scripts":{"test":"npm run lint && npm run spec && npm run coverage","spec":"NODE_PATH=lib NODE_ENV=test istanbul cover node_modules/.bin/_mocha -- -r test/helpers/chai -r test/helpers/sinon -R spec test/spec","lint":"eslint --ignore-path .gitignore .","coverage":"istanbul check-coverage --statement 100 --branch 100 --function 100"},"main":"lib/accepts.js","peerDependencies":{"express":"4.x"},"devDependencies":{"express":"4.x","eslint":"*","eslint-plugin-nodeca":"*","mocha":"*","istanbul":"*","chai":"*","chai-things":"*","sinon":"*","sinon-chai":"*","supertest":"*","supertest-chai":"*"},"description":"Express middleware to help you manage the HTTP Accept header.","versions":[{"number":"0.1.0","date":"2014-10-07T02:17:20.776Z"}],"readme":"# accepts\n\nExpress middleware to help you manage the HTTP Accept header.\n\nBasic usage:\n```javascript\nvar app = express();\napp.get('/api', accepts('application/json'), function(req, res) {\n\t// Only if Accept: application/json is true\n\treturn res.status(200).send({ hello: 'world' });\n});\n```\n\nUse fancier routing:\n```javascript\nvar app = express();\napp.get('/', accepts('text/html', 'application/json'));\napp.get('/', accepts.on('text/html'), function(req, res) {\n\treturn res.status(200).render('index');\n});\napp.get('/', accepts.on('application/json'), function(req, res) {\n\treturn res.status(200).send({ hello: 'world' });\n});\n```\n","created":"2014-10-07T02:17:20.776Z","modified":"2014-10-07T02:17:20.776Z","lastPublisher":{"name":"izaakschroeder","email":"izaak.schroeder@gmail.com"},"owners":[{"name":"izaakschroeder","email":"izaak.schroeder@gmail.com"}],"other":{"_attachments":{},"_from":".","_id":"express-accepts","_npmUser":{"name":"izaakschroeder","email":"izaak.schroeder@gmail.com"},"_npmVersion":"1.4.9","_rev":"1-1e68e43abf20ff30224f5e119fe47c66","_shasum":"04554f428a4cd8fc4ee5bdc572eb242aa445a0f0","author":{"name":"Izaak Schroeder","email":"izaak.schroeder@gmail.com"},"directories":{},"dist-tags":{"latest":"0.1.0"},"dist":{"shasum":"04554f428a4cd8fc4ee5bdc572eb242aa445a0f0","tarball":"http://registry.npmjs.org/express-accepts/-/express-accepts-0.1.0.tgz"},"maintainers":[{"name":"izaakschroeder","email":"izaak.schroeder@gmail.com"}],"readmeFilename":"README.md","time":{"modified":"2014-10-07T02:17:20.776Z","created":"2014-10-07T02:17:20.776Z","0.1.0":"2014-10-07T02:17:20.776Z"}}}