{"name":"gulp-http-post","version":"0.1.4","description":"Post buffer to current url on pipe, and handle http responses","main":"index.js","scripts":{"test":"istanbul cover ./node_modules/mocha/bin/_mocha -report lcovonly"},"repository":"https://github.com/gjurgens/gulp-http-post","keywords":["gulp","gulpplugin","post"],"homepage":"https://github.com/gjurgens/gulp-http-post","license":"MIT","dependencies":{"gulp-util":"^3.0.7","request":"^2.69.0","through2":"^2.0.1"},"devDependencies":{"chai":"^3.5.0","eslint":"^2.5.3","gulp":"^3.9.1","istanbul":"^0.4.5","mocha":"^2.4.5"},"gitHead":"485c937a8395ca6dbca45c967e9afe0bb27219cc","deprecated":"Please use gulp-http-put","readme":"# gulp-http-post \n> froked from [zhso/gulp-post](https://github.com/zhso/gulp-post)\n\n[![NPM](https://nodei.co/npm/gulp-http-post.png?downloads=true&downloadRank=true&stars=true)][npm-url][![NPM](https://nodei.co/npm-dl/gulp-http-post.png?height=3&months=6)][npm-url]\n\n[![npm](https://img.shields.io/npm/v/gulp-http-post.svg)][npm-url] [![npm](https://img.shields.io/npm/dm/gulp-http-post.svg)][npm-url] [![npm](https://david-dm.org/gjurgens/gulp-http-post.svg)][npm-url] [![npm](https://img.shields.io/npm/l/gulp-http-post.svg)][npm-url]\n\n[![bitHound Overall Score](https://www.bithound.io/github/gjurgens/gulp-http-post/badges/score.svg)](https://www.bithound.io/github/gjurgens/gulp-http-post) [![Inline docs](http://inch-ci.org/github/gjurgens/gulp-http-post.svg?branch=master)](http://inch-ci.org/github/gjurgens/gulp-http-post) [![Build Status](https://travis-ci.org/gjurgens/gulp-http-post.svg?branch=master)](https://travis-ci.org/gjurgens/gulp-http-post) [![Coverage Status](https://coveralls.io/repos/github/gjurgens/gulp-http-post/badge.svg?branch=master)](https://coveralls.io/github/gjurgens/gulp-http-post?branch=master)\n\n[![GitHub stars](https://img.shields.io/github/stars/gjurgens/gulp-http-post.svg?style=social&label=Star)](https://github.com/gjurgens/gulp-http-post/stargazers) [![GitHub watchers](https://img.shields.io/github/watchers/gjurgens/gulp-http-post.svg?style=social&label=Watch)](https://github.com/gjurgens/gulp-http-post/subscription)\n\n[npm-url]: https://npmjs.org/package/gulp-http-post\nPost buffer to current url on pipe.\n\n```js\nvar post = require(\"gulp-http-post\");\n\ngulp.task(\"post\",function(){\n    gulp.src(\"src/**/*.js\")\n        .pipe(post(\"http://www.mysite.com/\"))\n        .pipe(gulp.dest(\"dist\"));\n});\n```\n\n## Features\n\n* Custom post params\n* Support buffer encoding\n* Support current callback\n* Callback gets body string and full http response object as params\n\n## Installation\n\n```bash\n$ npm i gulp-http-post\n```\n\n## Examples\n\n* Custom Options\n\n```js\nvar post = new require(\"gulp-http-post\");\n\ngulp.task(\"build\",function(){\n    var options = {\n                encoding: \"base64\",\n                callback: function (err, body, response) {\n                    if(err){\n                        console.error(err);\n                    }else{\n                        console.log(body);\n                        console.log(response);\n                    }\n                },\n                param1: \"value1\",\n                param2: \"value2\"\n                //...\n    };\n    gulp.src(\"src/**/*.js\")\n        .pipe(post(\"http://www.mysite.com/\",options))\n        .pipe(gulp.dest(\"dist\"));\n})\n```\n\n## Options Format\n\n* **options.content** file content\n* **options.encoding** buffer.toString() encoding\n* **options.relative** file relative","versions":[{"number":"1.0.0","date":"2016-06-17T10:03:11.307Z"},{"number":"1.0.1","date":"2016-06-17T10:20:40.476Z"},{"number":"1.0.2","date":"2016-06-17T13:16:14.887Z"},{"number":"0.0.2","date":"2016-08-31T22:39:24.472Z"},{"number":"0.0.3","date":"2016-08-31T22:58:52.105Z"},{"number":"0.1.0","date":"2016-08-31T23:09:29.123Z"},{"number":"0.1.1","date":"2016-08-31T23:12:40.850Z"},{"number":"0.1.2","date":"2016-08-31T23:14:57.403Z"},{"number":"0.1.3","date":"2016-08-31T23:38:17.285Z"},{"number":"0.1.4","date":"2016-08-31T23:48:06.487Z"}],"created":"2016-06-17T10:03:11.307Z","modified":"2016-09-01T21:58:12.789Z","lastPublisher":{"name":"gjurgens","email":"gabriel@jurgens.com.ar"},"owners":[{"name":"gjurgens","email":"gabriel@jurgens.com.ar"}],"other":{"_attachments":{},"_from":".","_id":"gulp-http-post","_nodeVersion":"4.2.0","_npmOperationalInternal":{"host":"packages-12-west.internal.npmjs.com","tmp":"tmp/gulp-http-post-0.1.4.tgz_1472687284742_0.5583017126191407"},"_npmUser":{"name":"gjurgens","email":"gabriel@jurgens.com.ar"},"_npmVersion":"2.14.7","_rev":"1-907d77e24b5b06e285478b369a082237","_shasum":"a3bae3a126b0b59a520b75653cb04a5040cd9d66","author":{"name":"gjurgens"},"bugs":{"url":"https://github.com/gjurgens/gulp-http-post/issues"},"directories":{},"dist-tags":{"latest":"0.1.4"},"dist":{"shasum":"a3bae3a126b0b59a520b75653cb04a5040cd9d66","tarball":"http://registry.npmjs.org/gulp-http-post/-/gulp-http-post-0.1.4.tgz"},"maintainers":[{"name":"gjurgens","email":"gabriel@jurgens.com.ar"}],"readmeFilename":"README.md","time":{"modified":"2016-09-01T21:58:12.789Z","created":"2016-06-17T10:03:11.307Z","1.0.0":"2016-06-17T10:03:11.307Z","1.0.1":"2016-06-17T10:20:40.476Z","1.0.2":"2016-06-17T13:16:14.887Z","0.0.2":"2016-08-31T22:39:24.472Z","0.0.3":"2016-08-31T22:58:52.105Z","0.1.0":"2016-08-31T23:09:29.123Z","0.1.1":"2016-08-31T23:12:40.850Z","0.1.2":"2016-08-31T23:14:57.403Z","0.1.3":"2016-08-31T23:38:17.285Z","0.1.4":"2016-08-31T23:48:06.487Z"}}}