{"name":"homebridge-http","version":"0.0.9","description":"http(s) plugin for Homebridge: https://github.com/nfarina/homebridge","license":"ISC","keywords":["homebridge-plugin"],"engines":{"node":">=0.12.0","homebridge":">=0.2.0"},"repository":"https://github.com/rudders/homebridge-http","dependencies":{"request":"^2.65.0","polling-to-event":">=2.0.2"},"gitHead":"f8a497ae79416f345c3aeb62f5284cbcef798146","homepage":"https://github.com/rudders/homebridge-http#readme","_resolved":"git+https://github.com/rudders/homebridge-http.git#f8a497ae79416f345c3aeb62f5284cbcef798146","scripts":{},"versions":[{"number":"0.0.1","date":"2015-11-05T06:24:23.601Z"},{"number":"0.0.2","date":"2015-11-05T22:15:22.233Z"},{"number":"0.0.3","date":"2015-11-20T20:21:22.013Z"},{"number":"0.0.4","date":"2015-12-18T01:41:55.297Z"},{"number":"0.0.7","date":"2015-12-28T17:26:34.328Z"},{"number":"0.0.8","date":"2015-12-28T17:38:09.034Z"},{"number":"0.0.9","date":"2016-02-16T09:22:04.907Z"}],"readme":"# homebridge-http\n\nSupports https devices on the HomeBridge Platform and provides a readable callback for getting the \"On\" and brightness level characteristics to Homekit.\n\n# Installation\n\n1. Install homebridge using: npm install -g homebridge\n2. Install homebridge-http using: npm install -g homebridge-http\n3. Update your configuration file. See sample-config.json in this repository for a sample. \n\n# Configuration\n\nThis module has recently been updated to support an additional method to read the power state of the device and the brightness level. Specify the `status_url` in your config.json that returns the status of the device as an integer (0 = off, 1 = on). \n\nSpecify the `brightnesslvl_url` to return the current brightness level as an integer.\n\nSwitch Handling and brightness Handling support 3 methods, yes for polling on app load, realtime for constant polling or no polling\n\nConfiguration sample:\n\n ```\n\"accessories\": [ \n\t{\n\t\t\"accessory\": \"Http\",\n\t\t\"name\": \"Alfresco Lamp\",\n\t\t\"switchHandling\": \"realtime\",\n\t\t\"http_method\": \"GET\",\n\t\t\"on_url\":      \"http://localhost/controller/1700/ON\",\n\t\t\"off_url\":     \"http://localhost/controller/1700/OFF\",\n\t\t\"status_url\":  \"http://localhost/status/100059\",\n\t\t\"service\": \"Light\",\n\t\t\"brightnessHandling\": \"yes\",\n\t\t\"brightness_url\":     \"http://localhost/controller/1707/%b\",\n\t\t\"brightnesslvl_url\":  \"http://localhost/status/100054\",\n\t\t\"sendimmediately\": \"\",\n\t\t\"username\" : \"\",\n\t\t\"password\" : \"\"\t\t\t\t\t    \n       } \n    ]\n```\n\n#ToDo\n\nComplete documentation and review a number of  forks","starsCount":15,"created":"2015-11-05T06:24:23.601Z","modified":"2017-05-22T07:22:05.683Z","lastPublisher":{"name":"rudders","email":"a.rudman@binarylight.com.au"},"owners":[{"name":"rudders","email":"a.rudman@binarylight.com.au"}],"other":{"_attachments":{},"_from":"git+https://github.com/rudders/homebridge-http.git","_id":"homebridge-http","_nodeVersion":"5.1.0","_npmOperationalInternal":{"host":"packages-9-west.internal.npmjs.com","tmp":"tmp/homebridge-http-0.0.9.tgz_1455614522900_0.3017259333282709"},"_npmUser":{"name":"rudders","email":"a.rudman@binarylight.com.au"},"_npmVersion":"3.7.1","_rev":"7-6ba3690559e509c05aaee880b89ce454","_shasum":"1965ab279b5089303dc7c85ad8a2acc0cf22716c","author":{"name":"Adrian Rudman"},"bugs":{"url":"https://github.com/rudders/homebridge-http/issues"},"contributors":[{"name":"NovaGL"},{"name":"David Parry"}],"directories":{},"dist-tags":{"latest":"0.0.9"},"dist":{"shasum":"1965ab279b5089303dc7c85ad8a2acc0cf22716c","tarball":"http://registry.npmjs.org/homebridge-http/-/homebridge-http-0.0.9.tgz"},"maintainers":[{"name":"rudders","email":"a.rudman@binarylight.com.au"}],"readmeFilename":"README.md","time":{"modified":"2017-05-22T07:22:05.683Z","created":"2015-11-05T06:24:23.601Z","0.0.1":"2015-11-05T06:24:23.601Z","0.0.2":"2015-11-05T22:15:22.233Z","0.0.3":"2015-11-20T20:21:22.013Z","0.0.4":"2015-12-18T01:41:55.297Z","0.0.7":"2015-12-28T17:26:34.328Z","0.0.8":"2015-12-28T17:38:09.034Z","0.0.9":"2016-02-16T09:22:04.907Z"},"users":{"japh":true,"safarikc":true,"nicknewlin":true,"grandefabio":true,"toshir8":true,"dosevader":true,"dmitriydef":true,"krital":true,"djk":true,"dingdangnao":true,"willnewii":true,"seeker5084":true,"egreenie":true,"sziszi":true,"redonebe":true}}}