{"name":"http_ece","version":"1.0.2","description":"Encrypted Content-Encoding for HTTP","homepage":"https://github.com/martinthomson/encrypted-content-encoding","repository":"https://github.com/martinthomson/encrypted-content-encoding","license":"MIT","main":"./ece.js","scripts":{"test":"node ./test.js"},"engines":{"node":">=4"},"dependencies":{"urlsafe-base64":"~1.0.0"},"versions":[{"number":"0.2.0","date":"2015-10-15T23:59:10.756Z"},{"number":"0.4.0","date":"2016-03-04T06:00:39.702Z"},{"number":"0.4.1","date":"2016-03-08T00:04:20.823Z"},{"number":"0.4.3","date":"2016-03-15T23:47:34.630Z"},{"number":"0.4.4","date":"2016-03-20T22:11:01.103Z"},{"number":"0.4.5","date":"2016-03-23T04:15:41.883Z"},{"number":"0.5.0","date":"2016-04-13T11:26:08.457Z"},{"number":"0.5.1","date":"2016-04-22T04:29:02.535Z"},{"number":"0.5.2","date":"2016-10-11T22:34:29.129Z"},{"number":"0.6.0","date":"2016-12-22T05:58:03.238Z"},{"number":"0.6.3","date":"2016-12-23T02:47:56.105Z"},{"number":"0.6.4","date":"2016-12-23T05:36:03.201Z"},{"number":"0.7.0","date":"2017-02-14T01:59:21.670Z"},{"number":"0.7.1","date":"2017-03-12T23:54:05.312Z"},{"number":"0.7.2","date":"2017-03-17T01:27:56.765Z"},{"number":"1.0.0","date":"2017-05-08T22:41:12.496Z"},{"number":"1.0.2","date":"2017-06-22T00:43:10.402Z"}],"readme":"# encrypted-content-encoding\n\nA simple implementation of the [HTTP encrypted\ncontent-encoding](https://tools.ietf.org/html/draft-nottingham-http-encryption-encoding)\n\n# Use\n\n```js\nvar ece = require('http_ece');\nvar crypto = require('crypto')\nvar base64 = require('base64url');\n\nvar parameters = {\n  key: base64.encode(crypto.randomBytes(16)),\n  salt: base64.encode(crypto.randomBytes(16))\n};\nvar encrypted = ece.encrypt(data, parameters);\n\nvar decrypted = ece.encrypt(encrypted, parameters);\n\nrequire('assert').equal(decrypted.compare(data), 0);\n```\n\nThis also supports the static-ephemeral ECDH mode.  The source explains how.\n\n# TODO\n\nUse the node streams API instead of the legacy APIs.\n","created":"2015-10-15T23:59:10.756Z","modified":"2017-06-22T00:43:10.402Z","lastPublisher":{"name":"martinthomson","email":"martin.thomson@gmail.com"},"owners":[{"name":"martinthomson","email":"martin.thomson@gmail.com"}],"other":{"_attachments":{},"_from":".","_id":"http_ece","_nodeVersion":"6.4.0","_npmOperationalInternal":{"host":"s3://npm-registry-packages","tmp":"tmp/http_ece-1.0.2.tgz_1498092190032_0.4338736373465508"},"_npmUser":{"name":"martinthomson","email":"martin.thomson@gmail.com"},"_npmVersion":"3.10.3","_rev":"9-ed16117874960f94b566ceda74ae7b09","_shasum":"7bc2a558399a096d09160d8d53ecfab18c479e9f","author":{"name":"Martin Thomson","email":"martin.thomson@gmail.com"},"bugs":{"url":"https://github.com/martinthomson/encrypted-content-encoding/issues"},"contributors":[{"name":"Marco Castelluccio","email":"mcastelluccio@mozilla.com"}],"directories":{},"dist-tags":{"latest":"1.0.2"},"dist":{"shasum":"7bc2a558399a096d09160d8d53ecfab18c479e9f","tarball":"https://registry.npmjs.org/http_ece/-/http_ece-1.0.2.tgz"},"maintainers":[{"name":"martinthomson","email":"martin.thomson@gmail.com"}],"readmeFilename":"README.md","time":{"modified":"2017-06-22T00:43:10.402Z","created":"2015-10-15T23:59:10.756Z","0.2.0":"2015-10-15T23:59:10.756Z","0.4.0":"2016-03-04T06:00:39.702Z","0.4.1":"2016-03-08T00:04:20.823Z","0.4.3":"2016-03-15T23:47:34.630Z","0.4.4":"2016-03-20T22:11:01.103Z","0.4.5":"2016-03-23T04:15:41.883Z","0.5.0":"2016-04-13T11:26:08.457Z","0.5.1":"2016-04-22T04:29:02.535Z","0.5.2":"2016-10-11T22:34:29.129Z","0.6.0":"2016-12-22T05:58:03.238Z","0.6.3":"2016-12-23T02:47:56.105Z","0.6.4":"2016-12-23T05:36:03.201Z","0.7.0":"2017-02-14T01:59:21.670Z","0.7.1":"2017-03-12T23:54:05.312Z","0.7.2":"2017-03-17T01:27:56.765Z","1.0.0":"2017-05-08T22:41:12.496Z","1.0.2":"2017-06-22T00:43:10.402Z"}}}