{"name":"http-error-stream","version":"1.0.1","description":"Stream an error over http","main":"index.js","scripts":{"deps":"dependency-check . && dependency-check . --extra --no-dev","test":"standard && npm run deps && NODE_ENV=test node test","test:cov":"standard && npm run deps && NODE_ENV=test istanbul cover test.js"},"repository":"https://github.com/yoshuawuyts/http-error-stream","keywords":["http","error","stream"],"license":"MIT","dependencies":{"from2-string":"^1.1.0","readable-stream":"^2.0.6"},"devDependencies":{"dependency-check":"^2.5.1","istanbul":"^0.4.2","tape":"^4.5.1"},"gitHead":"5b8849d5782611f00b425e0ae7af490817f6f44b","homepage":"https://github.com/yoshuawuyts/http-error-stream#readme","versions":[{"number":"1.0.1","date":"2016-03-29T08:47:53.350Z"}],"readme":"# http-error-stream [![stability][1]][1]\n[![npm version][2]][3] [![build status][4]][5] [![test coverage][6]][7]\n[![downloads][8]][9] [![js-standard-style][10]][11]\n\nStream an error over http. Takes a `server-error` error and streams it back\nout.\n\n## Usage\n```js\nconst errorStream = require('http-error-stream')\nconst serverError = require('server-error')\nconst bole = require('bole')\nconst http = require('http')\n\nconst log = bole('my-service')\nconst error = serverError(log)\n\nhttp.createServer(function (req, res) {\n  const err = error.client('oh no!')\n  // set statusCode, content-type and stream error as JSON\n  errorStream(req, res, err).pipe(res)\n}).listen\n```\n\n## Installation\n```sh\n$ npm install http-error-stream\n```\n\n## License\n[MIT](https://tldrlegal.com/license/mit-license)\n\n[0]: https://img.shields.io/badge/stability-experimental-orange.svg?style=flat-square\n[1]: https://nodejs.org/api/documentation.html#documentation_stability_index\n[2]: https://img.shields.io/npm/v/http-error-stream.svg?style=flat-square\n[3]: https://npmjs.org/package/http-error-stream\n[4]: https://img.shields.io/travis/yoshuawuyts/http-error-stream/master.svg?style=flat-square\n[5]: https://travis-ci.org/yoshuawuyts/http-error-stream\n[6]: https://img.shields.io/codecov/c/github/yoshuawuyts/http-error-stream/master.svg?style=flat-square\n[7]: https://codecov.io/github/yoshuawuyts/http-error-stream\n[8]: http://img.shields.io/npm/dm/http-error-stream.svg?style=flat-square\n[9]: https://npmjs.org/package/http-error-stream\n[10]: https://img.shields.io/badge/code%20style-standard-brightgreen.svg?style=flat-square\n[11]: https://github.com/feross/standard\n","created":"2016-03-29T08:47:53.350Z","modified":"2016-03-29T08:47:53.350Z","lastPublisher":{"name":"yoshuawuyts","email":"i@yoshuawuyts.com"},"owners":[{"name":"yoshuawuyts","email":"i@yoshuawuyts.com"}],"other":{"_attachments":{},"_from":".","_id":"http-error-stream","_nodeVersion":"5.9.1","_npmOperationalInternal":{"host":"packages-12-west.internal.npmjs.com","tmp":"tmp/http-error-stream-1.0.1.tgz_1459241272916_0.9902577546890825"},"_npmUser":{"name":"yoshuawuyts","email":"i@yoshuawuyts.com"},"_npmVersion":"2.15.2","_rev":"1-9b6cc676030231a4f1c4623984c97f37","_shasum":"c3840043d07221b761319557777bbad679d6273a","bugs":{"url":"https://github.com/yoshuawuyts/http-error-stream/issues"},"directories":{},"dist-tags":{"latest":"1.0.1"},"dist":{"shasum":"c3840043d07221b761319557777bbad679d6273a","tarball":"http://registry.npmjs.org/http-error-stream/-/http-error-stream-1.0.1.tgz"},"maintainers":[{"name":"yoshuawuyts","email":"i@yoshuawuyts.com"}],"readmeFilename":"README.md","time":{"modified":"2016-03-29T08:47:53.350Z","created":"2016-03-29T08:47:53.350Z","1.0.1":"2016-03-29T08:47:53.350Z"}}}