{"name":"istin","version":"0.1.5","description":"Simple and readable http framework for node.js","main":"index.js","scripts":{"test":"echo \"Error: no test specified\" && exit 1"},"license":"ISC","dependencies":{"coffee-script":"^1.10.0"},"gitHead":"21748975f9ec98f02915fe329628f0ab795aa6c2","versions":[{"number":"1.0.0","date":"2015-10-15T13:32:31.375Z"},{"number":"0.1.0","date":"2015-10-15T13:34:05.912Z"},{"number":"0.1.1","date":"2015-10-15T14:24:19.863Z"},{"number":"0.1.2","date":"2015-10-15T14:48:33.113Z"},{"number":"0.1.4","date":"2015-10-15T15:20:51.134Z"},{"number":"0.1.5","date":"2015-10-17T11:34:42.693Z"}],"readme":"# Istin\n\nSimple and readable http framework for node.js\n\n\n### Reference in development\n","created":"2015-10-15T13:32:31.375Z","modified":"2015-10-17T11:34:42.693Z","lastPublisher":{"name":"pleshevskiy","email":"pleshevskiy@gmail.com"},"owners":[{"name":"pleshevskiy","email":"pleshevskiy@gmail.com"}],"other":{"_attachments":{},"_from":".","_id":"istin","_nodeVersion":"4.0.0","_npmUser":{"name":"pleshevskiy","email":"pleshevskiy@gmail.com"},"_npmVersion":"2.14.3","_rev":"1-627603989a773b3275bcaaeeb2e6a8ee","_shasum":"ede03bde170cee85d474c53bb78cf5d09cab7278","author":{"name":"Pleshevskiy","email":"pleshevkiy@gmail.com"},"directories":{},"dist-tags":{"latest":"0.1.5"},"dist":{"shasum":"ede03bde170cee85d474c53bb78cf5d09cab7278","tarball":"http://registry.npmjs.org/istin/-/istin-0.1.5.tgz"},"maintainers":[{"name":"pleshevskiy","email":"pleshevskiy@gmail.com"}],"readmeFilename":"README.md","time":{"modified":"2015-10-17T11:34:42.693Z","created":"2015-10-15T13:32:31.375Z","1.0.0":"2015-10-15T13:32:31.375Z","0.1.0":"2015-10-15T13:34:05.912Z","0.1.1":"2015-10-15T14:24:19.863Z","0.1.2":"2015-10-15T14:48:33.113Z","0.1.4":"2015-10-15T15:20:51.134Z","0.1.5":"2015-10-17T11:34:42.693Z"}}}