{"name":"lime-transport-http","version":"3.1.0","description":"HTTP transport class for the LIME protocol","main":"HttpTransport.js","files":["HttpTransport.js"],"scripts":{"test":"mocha ./test --recursive","test:watch":"mocha ./test --recursive -w","preversion":"npm test","postversion":"git push && git push --tags && npm publish"},"repository":"https://github.com/takenet/lime-js-transports","keywords":["lime","http","transport"],"license":"MIT","homepage":"https://github.com/takenet/lime-js-transports#readme","dependencies":{"lime-js":"^2.0.1","node-fetch":"^1.6.3"},"devDependencies":{"body-parser":"^1.15.2","chai":"^3.5.0","express":"^4.14.0","js-base64":"^2.1.9","mocha":"^2.5.3"},"versions":[{"number":"1.0.0","date":"2016-12-29T16:18:34.084Z"},{"number":"2.0.0","date":"2016-12-30T17:45:11.723Z"},{"number":"2.0.1","date":"2017-01-18T15:27:53.829Z"},{"number":"2.0.2","date":"2017-01-23T15:33:02.713Z"},{"number":"2.0.3","date":"2017-01-23T16:39:02.147Z"},{"number":"3.0.0","date":"2017-01-24T16:49:29.170Z"},{"number":"3.1.0","date":"2017-02-10T11:32:54.139Z"}],"readme":"ERROR: No README data found!","created":"2016-12-29T16:18:34.084Z","modified":"2017-02-10T12:17:35.393Z","lastPublisher":{"name":"arthur-xavier","email":"arthur.xavierx@gmail.com"},"owners":[{"name":"arthur-xavier","email":"arthur.xavierx@gmail.com"},{"name":"luizguicl","email":"luizguicl@gmail.com"},{"name":"ravpacheco","email":"ravpacheco@gmail.com"},{"name":"takenet","email":"andreb@takenet.com.br"},{"name":"victorbalbo","email":"Victorbalbo@gmail.com"}],"other":{"_attachments":{},"_from":".","_id":"lime-transport-http","_nodeVersion":"5.3.0","_npmOperationalInternal":{"host":"packages-18-east.internal.npmjs.com","tmp":"tmp/lime-transport-http-3.1.0.tgz_1486726372311_0.26307590189389884"},"_npmUser":{"name":"arthur-xavier","email":"arthur.xavierx@gmail.com"},"_npmVersion":"3.3.12","_rev":"11-89d54a05c396949b1211969f027217b2","_shasum":"054df22ac2492953542ba1aa41d31c2b4657b6da","bugs":{"url":"https://github.com/takenet/lime-js-transports/issues"},"directories":{},"dist-tags":{"latest":"3.1.0"},"dist":{"shasum":"054df22ac2492953542ba1aa41d31c2b4657b6da","tarball":"https://registry.npmjs.org/lime-transport-http/-/lime-transport-http-3.1.0.tgz"},"maintainers":[{"name":"arthur-xavier","email":"arthur.xavierx@gmail.com"},{"name":"luizguicl","email":"luizguicl@gmail.com"},{"name":"ravpacheco","email":"ravpacheco@gmail.com"},{"name":"takenet","email":"andreb@takenet.com.br"},{"name":"victorbalbo","email":"Victorbalbo@gmail.com"}],"readmeFilename":"","time":{"modified":"2017-02-10T12:17:35.393Z","created":"2016-12-29T16:18:34.084Z","1.0.0":"2016-12-29T16:18:34.084Z","2.0.0":"2016-12-30T17:45:11.723Z","2.0.1":"2017-01-18T15:27:53.829Z","2.0.2":"2017-01-23T15:33:02.713Z","2.0.3":"2017-01-23T16:39:02.147Z","3.0.0":"2017-01-24T16:49:29.170Z","3.1.0":"2017-02-10T11:32:54.139Z"}}}