{"name":"req-logger","version":"2.0.0","description":"Simple http request logging","main":"index.js","scripts":{"test":"node test.js && standard","example":"node example.js"},"keywords":[],"license":"MIT","dependencies":{"client-ip":"^1.0.0","end-of-stream":"^1.1.0","xtend":"^4.0.1"},"devDependencies":{"servertest":"^1.2.1","standard":"^5.4.1","tape":"^4.2.2"},"repository":"https://github.com/davidguttman/req-logger","homepage":"https://github.com/davidguttman/req-logger#readme","gitHead":"40da95fc2a9b56bfc555049b6c669836beebb455","versions":[{"number":"1.0.0","date":"2015-11-25T20:42:29.925Z"},{"number":"1.1.0","date":"2015-12-02T16:34:44.157Z"},{"number":"2.0.0","date":"2017-03-02T02:22:00.358Z"}],"readme":"# ReqLogger #\n\nSimple HTTP request logging.\n\nDefaults: `responseTime`, `method`, `url`, `statusCode`\n\n## Example ##\n\n```js\nvar http = require('http')\nvar ReqLogger = require('req-logger')\n\nvar logger = ReqLogger({\n  version: require('./package.json').version // will show on every request\n})\n\nvar server = http.createServer(function (req, res) {\n  logger(req, res, {\n    timestamp: new Date() // will show just this once\n  })\n\n  res.writeHead(200)\n  setTimeout(function () {\n    res.end('DELAYED')\n    server.close()\n  }, 250)\n})\n\nserver.listen(1337)\n\n// Example output:\n// { ip: '127.0.0.1',\n//   method: 'GET',\n//   url: '/',\n//   userAgent: 'Mozilla/5.0 (Macintosh; Intel Mac OS X 10_11_1) AppleWebKit/537// .36 (KHTML, like Gecko) Chrome/46.0.2490.86 Safari/537.36',\n//   responseTime: 255,\n//   statusCode: 200,\n//   version: '1.0.0',\n//   timestamp: Wed Nov 25 2015 11:58:44 GMT-0800 (PST) }\n\n```\n\n## API ##\n\n### ReqLogger([opts, cb]) ###\n\n`ReqLogger()` is the main entry point. Accepts optional `opts` (default is `{}`) and optional `cb` (default is `console.log`). Returns a logging function `logger`.\n\n```js\nvar logger = ReqLogger()\n\n// or\n\nvar logger = ReqLogger({version: '1.2.3'}) // shows on every log\n\n// or\nvar log = bunyan.createLogger({name: 'requests'})\nvar logger = ReqLogger(function(obj) {\n  log.info(obj) // custom logging\n})\n\n// logger is now a function that takes req and res as arguments\n```\n\n### logger(req, res, [opts, cb]) ###\n\n`logger()` -- call this function when you actually want to log a request. `req` and `res` are required. Accepts `opts` and `cb` like `ReqLogger()` above, but will only apply to the single call. Useful for adding a user or timestamp that isn't on the `req` object.\n\n# License #\n\nMIT\n","created":"2015-11-25T20:42:29.925Z","modified":"2017-03-02T02:22:00.358Z","lastPublisher":{"name":"dguttman","email":"david@davidguttman.com"},"owners":[{"name":"dguttman","email":"david@davidguttman.com"}],"other":{"_attachments":{},"_from":".","_id":"req-logger","_nodeVersion":"6.9.1","_npmOperationalInternal":{"host":"packages-18-east.internal.npmjs.com","tmp":"tmp/req-logger-2.0.0.tgz_1488421319745_0.014714153250679374"},"_npmUser":{"name":"dguttman","email":"david@davidguttman.com"},"_npmVersion":"3.10.8","_rev":"2-9bacfa55903931224a3b37e0f5734039","_shasum":"cbdd9abec236601d63d4213cd9bb0451a7aa2350","author":{"name":"David Guttman","email":"david@guttman.io","url":"http://davidguttman.com/"},"bugs":{"url":"https://github.com/davidguttman/req-logger/issues"},"directories":{},"dist-tags":{"latest":"2.0.0"},"dist":{"shasum":"cbdd9abec236601d63d4213cd9bb0451a7aa2350","tarball":"https://registry.npmjs.org/req-logger/-/req-logger-2.0.0.tgz"},"maintainers":[{"name":"dguttman","email":"david@davidguttman.com"}],"readmeFilename":"README.md","time":{"modified":"2017-03-02T02:22:00.358Z","created":"2015-11-25T20:42:29.925Z","1.0.0":"2015-11-25T20:42:29.925Z","1.1.0":"2015-12-02T16:34:44.157Z","2.0.0":"2017-03-02T02:22:00.358Z"}}}