{"name":"whakaruru-watch","version":"1.0.0","description":"Zero downtime automatically reloading http server","main":"index.js","scripts":{"test":"echo \"Error: no test specified\" && exit 1"},"repository":"https://github.com/metocean/whakaruru-watch","license":"MIT","homepage":"https://github.com/metocean/whakaruru-watch#readme","dependencies":{"chokidar":"1.4.0","debounce":"1.0.0","whakaruru":"1.0.2"},"gitHead":"c3d6ca8b1da33477b9a103974de8e9bf64a83c75","versions":[{"number":"1.0.0","date":"2015-12-09T00:04:49.721Z"}],"readme":"# whakaruru-watch\nZero downtime automatically reloading http server\n","created":"2015-12-09T00:04:49.721Z","modified":"2015-12-13T20:54:30.240Z","lastPublisher":{"name":"tcoats","email":"npm@voodoolabs.net"},"owners":[{"name":"ascendzor","email":"wow.troymare@gmail.com"},{"name":"tcoats","email":"npm@voodoolabs.net"}],"other":{"_attachments":{},"_from":".","_id":"whakaruru-watch","_nodeVersion":"5.1.1","_npmUser":{"name":"tcoats","email":"npm@voodoolabs.net"},"_npmVersion":"3.3.12","_rev":"1-f9dfec146b2cffb7a3453f095180dcb9","_shasum":"f40b90acd72054e0057bde9031d955b5f44bde20","author":{"name":"Thomas Coats","email":"t.coats@metocean.co.nz"},"bugs":{"url":"https://github.com/metocean/whakaruru-watch/issues"},"directories":{},"dist-tags":{"latest":"1.0.0"},"dist":{"shasum":"f40b90acd72054e0057bde9031d955b5f44bde20","tarball":"http://registry.npmjs.org/whakaruru-watch/-/whakaruru-watch-1.0.0.tgz"},"maintainers":[{"name":"ascendzor","email":"wow.troymare@gmail.com"},{"name":"tcoats","email":"npm@voodoolabs.net"}],"readmeFilename":"README.md","time":{"modified":"2015-12-13T20:54:30.240Z","created":"2015-12-09T00:04:49.721Z","1.0.0":"2015-12-09T00:04:49.721Z"}}}